{
  "project_info": {
    "project_number": "945331839593",
    "project_id": "tenshoku-and",
    "storage_bucket": "tenshoku-and.appspot.com"
  },
  "client": [
    {
      "client_info": {
        "mobilesdk_app_id": "1:945331839593:android:ef11b2858c520d005e78f8",
        "android_client_info": {
          "package_name": "com.example.tenshoku_and.prod"
        }
      },
      "oauth_client": [],
      "api_key": [
        {
          "current_key": "AIzaSyAobUaKtx5fIwzXd35Md5eEplE2MaZCWxw"
        }
      ],
      "services": {
        "appinvite_service": {
          "other_platform_oauth_client": []
        }
      }
    },
    {
      "client_info": {
        "mobilesdk_app_id": "1:945331839593:android:de8fa02108ef281a5e78f8",
        "android_client_info": {
          "package_name": "com.example.tokitoki.prod"
        }
      },
      "oauth_client": [],
      "api_key": [
        {
          "current_key": "AIzaSyAobUaKtx5fIwzXd35Md5eEplE2MaZCWxw"
        }
      ],
      "services": {
        "appinvite_service": {
          "other_platform_oauth_client": []
        }
      }
    }
  ],
  "configuration_version": "1"
}